[
  {
    "차종": "아이오닉5",
    "차량상태": "가용",
    "트림": "익스클루시브",
    "옵션": "컴포트",
    "외장색": "아틀라스화이트",
    "내장색": "블랙",
    "생산번호": "I5AB12345",
    "출고센터": "인천",
    "생산일": "2025-06-12",
    "판매코드_d": "D1425",
    "판매코드_e": "E1200",
    "판매코드_f": "F0901",
    "판매코드_g": "G5520",
    "판매가": 43500000,
    "조건_계": "-200만원"
  },
  {
    "차종": "넥쏘",
    "차량상태": "가용",
    "트림": "모던",
    "옵션": "스마트센스",
    "외장칼라": "화이트",
    "내장칼라": "블랙",
    "생산번호": "NXO112233",
    "출고센터": "부천",
    "생산일": "2025-05-30",
    "판매코드_d": "D1500",
    "판매코드_e": "E2200",
    "판매코드_f": "F1001",
    "판매코드_g": "G6000",
    "판매가": 68500000,
    "조건 계": "-300만원"
  }
]